pylock_attestations/__init__.py
pylock_attestations/__main__.py
pylock_attestations/_cli.py
pylock_attestations/py.typed
pylock_attestations/_vendor/packaging/__init__.py
pylock_attestations/_vendor/packaging/_elffile.py
pylock_attestations/_vendor/packaging/_manylinux.py
pylock_attestations/_vendor/packaging/_musllinux.py
pylock_attestations/_vendor/packaging/_parser.py
pylock_attestations/_vendor/packaging/_structures.py
pylock_attestations/_vendor/packaging/_tokenizer.py
pylock_attestations/_vendor/packaging/markers.py
pylock_attestations/_vendor/packaging/metadata.py
pylock_attestations/_vendor/packaging/py.typed
pylock_attestations/_vendor/packaging/pylock.py
pylock_attestations/_vendor/packaging/requirements.py
pylock_attestations/_vendor/packaging/specifiers.py
pylock_attestations/_vendor/packaging/tags.py
pylock_attestations/_vendor/packaging/utils.py
pylock_attestations/_vendor/packaging/version.py
pylock_attestations/_vendor/packaging/licenses/__init__.py
pylock_attestations/_vendor/packaging/licenses/_spdx.py
pylock_attestations-0.0.1a2.dist-info/licenses/LICENSE
pylock_attestations-0.0.1a2.dist-info/METADATA
pylock_attestations-0.0.1a2.dist-info/WHEEL
pylock_attestations-0.0.1a2.dist-info/entry_points.txt
pylock_attestations-0.0.1a2.dist-info/top_level.txt
pylock_attestations-0.0.1a2.dist-info/RECORD
