Metadata-Version: 2.4
Name: pylock-attestations
Version: 0.0.1a2
Summary: CLI tool to add attestation identities to a pylock.toml file
Author-email: Trail of Bits <opensource@trailofbits.com>
License-Expression: Apache-2.0
Project-URL: Homepage, https://pypi.org/project/pylock-attestations
Project-URL: Documentation, https://trailofbits.github.io/pylock-attestations/
Project-URL: Issues, https://github.com/trailofbits/pylock-attestations/issues
Project-URL: Source, https://github.com/trailofbits/pylock-attestations
Classifier: Programming Language :: Python :: 3
Requires-Python: >=3.13
License-File: LICENSE
Requires-Dist: pypi-attestations==0.0.25
Requires-Dist: tomli-w>=1.2.0
Provides-Extra: doc
Requires-Dist: pdoc; extra == "doc"
Provides-Extra: test
Requires-Dist: pytest; extra == "test"
Requires-Dist: pytest-cov; extra == "test"
Requires-Dist: pretend; extra == "test"
Requires-Dist: coverage[toml]; extra == "test"
Provides-Extra: lint
Requires-Dist: ruff~=0.11.8; extra == "lint"
Requires-Dist: mypy>=1.0; extra == "lint"
Requires-Dist: types-html5lib; extra == "lint"
Requires-Dist: types-requests; extra == "lint"
Requires-Dist: types-toml; extra == "lint"
Requires-Dist: interrogate; extra == "lint"
Provides-Extra: dev
Requires-Dist: pylock-attestations[doc,lint,test]; extra == "dev"
Requires-Dist: twine; extra == "dev"
Requires-Dist: build; extra == "dev"
Dynamic: license-file
